{
  "generated_at": "2026-07-18T04:14:00.781692+00:00",
  "resources": {
    "frontend": {
      "status": "ok",
      "latency_ms": 179,
      "detail": "HTTP 200"
    },
    "backend": {
      "status": "warn",
      "latency_ms": 32242,
      "detail": "HTTP 200 \u2014 possivel cold start (free tier ocioso)"
    },
    "database": {
      "status": "ok",
      "latency_ms": 364,
      "detail": "SELECT 1 ok"
    },
    "storage": {
      "status": "ok",
      "latency_ms": 333,
      "detail": "HTTP 200"
    }
  }
}